knpay_plugin/__init__.py
knpay_plugin/admin.py
knpay_plugin/api.py
knpay_plugin/apps.py
knpay_plugin/conf.py
knpay_plugin/data.py
knpay_plugin/fields.py
knpay_plugin/forms.py
knpay_plugin/models.py
knpay_plugin/tests.py
knpay_plugin/urls.py
knpay_plugin/views.py
knpay_plugin/locale/ar/LC_MESSAGES/django.mo
knpay_plugin/locale/ar/LC_MESSAGES/django.po
knpay_plugin/migrations/0001_initial.py
knpay_plugin/migrations/0002_auto_20170321_1110.py
knpay_plugin/migrations/0003_auto_20170403_0950.py
knpay_plugin/migrations/0004_paymenttransaction_payment_url.py
knpay_plugin/migrations/0005_auto_20170414_0713.py
knpay_plugin/migrations/__init__.py
knpay_plugin/static/knpay_plugin/images/cybersource.jpg
knpay_plugin/static/knpay_plugin/images/knet.jpg
knpay_plugin/static/knpay_plugin/images/master-card.jpg
knpay_plugin/static/knpay_plugin/images/paypal.jpg
knpay_plugin/static/knpay_plugin/images/visa-card.jpg
knpay_plugin/templates/knpay_plugin/gateway_choices.html
knpay_plugin/templates/knpay_plugin/payment_details.html
knpay_plugin/templates/knpay_plugin/payment_method.html
knpay_plugin/templatetags/__init__.py
knpay_plugin/templatetags/knpay_tags.py
knpay_plugin-0.2.7.dist-info/AUTHORS.rst
knpay_plugin-0.2.7.dist-info/LICENSE
knpay_plugin-0.2.7.dist-info/METADATA
knpay_plugin-0.2.7.dist-info/WHEEL
knpay_plugin-0.2.7.dist-info/top_level.txt
knpay_plugin-0.2.7.dist-info/RECORD
