Metadata-Version: 2.1
Name: knpay-plugin
Version: 0.2.7
Summary: connects knpay into your project
Home-page: https://bitbucket.org/KuwaitNET/knpay_plugin
Author: Dacian Popute
Author-email: dacian@kuwaitnet.com
License: UNKNOWN
Keywords: knpay_plugin
Platform: UNKNOWN
Classifier: Development Status :: 3 - Alpha
Classifier: Framework :: Django
Classifier: Framework :: Django :: 2.2
Classifier: Intended Audience :: Developers
Classifier: License :: OSI Approved :: BSD License
Classifier: Natural Language :: English
Classifier: Programming Language :: Python :: 3.6
Classifier: Programming Language :: Python :: 3.7
Classifier: Programming Language :: Python :: 3.8
Requires-Dist: django (>=2.2)
Requires-Dist: django-jsonfield (==1.4.0)
Requires-Dist: django-appconf (>=1.0.2)
Requires-Dist: django-fsm (>=2.6.1)
Requires-Dist: requests (>=2.13.0)
Requires-Dist: six (>=1.11)
